dexplot/__init__.py
dexplot/_common_plot.py
dexplot/_heat.py
dexplot/_plots.py
dexplot/_utils.py
dexplot/colors/__init__.py
dexplot/colors/_app.py
dexplot/colors/_categories.py
dexplot/colors/_colormaps.py
tests/__init__.py
tests/test_bar.py
tests/test_box.py
tests/test_line.py
tests/test_scatter.py
dexplot-0.1.4.dist-info/LICENSE
dexplot-0.1.4.dist-info/METADATA
dexplot-0.1.4.dist-info/WHEEL
dexplot-0.1.4.dist-info/top_level.txt
dexplot-0.1.4.dist-info/RECORD
