Metadata-Version: 2.1
Name: dexplot
Version: 0.1.4
Summary: Powerful and intuitive data visualization library using matplotlib for both long and wide data
Home-page: https://github.com/dexplo/dexplot
Author: Ted Petrou
Author-email: petrou.theodore@gmail.com
License: UNKNOWN
Keywords: data visualization matplotlib pandas
Platform: UNKNOWN
Classifier: Programming Language :: Python :: 3
Classifier: License :: OSI Approved :: BSD License
Classifier: Operating System :: OS Independent
Classifier: Framework :: Matplotlib
Requires-Python: >=3.6
Requires-Dist: numpy (>=1.15)
Requires-Dist: scipy (>=1.0matplotlib>=3.1)
Requires-Dist: pandas (>=0.24)
Provides-Extra: apps
Requires-Dist: ipywidgets ; extra == 'apps'
